{
  "date": "2025-12-10",
  "projects": {
    "totem2": {
      "totalLinesAdded": 20,
      "totalLinesRemoved": 0,
      "totalActiveTime": 0,
      "files": {
        "c:\\Users\\thiag\\AppData\\Roaming\\Code\\User\\globalStorage\\yunusga.ftp-simple\\remote-workspace-temp\\37045e2986e0b0e4b66c2134e9be553d\\web\\EXTRA\\OFICINA\\enviar-mails.php": [
          {
            "timestamp": "2025-12-10T15:46:59.116Z",
            "fileName": "c:\\Users\\thiag\\AppData\\Roaming\\Code\\User\\globalStorage\\yunusga.ftp-simple\\remote-workspace-temp\\37045e2986e0b0e4b66c2134e9be553d\\web\\EXTRA\\OFICINA\\enviar-mails.php",
            "fileType": ".php",
            "linesAdded": 20,
            "linesRemoved": 0,
            "projectName": "totem2",
            "content": {
              "added": [],
              "removed": []
            },
            "duration": 0,
            "language": "php"
          }
        ]
      },
      "languageStats": {
        "php": 0
      },
      "changeFrequency": {
        "12": 0
      },
      "topFiles": [
        "c:\\Users\\thiag\\AppData\\Roaming\\Code\\User\\globalStorage\\yunusga.ftp-simple\\remote-workspace-temp\\37045e2986e0b0e4b66c2134e9be553d\\web\\EXTRA\\OFICINA\\enviar-mails.php"
      ],
      "averageChangeSize": 20
    }
  },
  "totalActiveTime": 0,
  "totalProjects": 1,
  "totalFiles": 1,
  "mostActiveHours": [
    12
  ],
  "mostUsedLanguages": [
    "php"
  ]
}