{
  "date": "2025-09-25",
  "projects": {
    "web": {
      "totalLinesAdded": 220,
      "totalLinesRemoved": 0,
      "totalActiveTime": 0,
      "files": {
        "c:\\Users\\thiag\\AppData\\Roaming\\Code\\User\\globalStorage\\yunusga.ftp-simple\\remote-workspace-temp\\37045e2986e0b0e4b66c2134e9be553d\\web\\head.php": [
          {
            "timestamp": "2025-09-25T11:38:51.992Z",
            "fileName": "c:\\Users\\thiag\\AppData\\Roaming\\Code\\User\\globalStorage\\yunusga.ftp-simple\\remote-workspace-temp\\37045e2986e0b0e4b66c2134e9be553d\\web\\head.php",
            "fileType": ".php",
            "linesAdded": 219,
            "linesRemoved": 0,
            "projectName": "web",
            "content": {
              "added": [],
              "removed": []
            },
            "duration": 0,
            "language": "php"
          },
          {
            "timestamp": "2025-09-25T13:58:46.117Z",
            "fileName": "c:\\Users\\thiag\\AppData\\Roaming\\Code\\User\\globalStorage\\yunusga.ftp-simple\\remote-workspace-temp\\37045e2986e0b0e4b66c2134e9be553d\\web\\head.php",
            "fileType": ".php",
            "linesAdded": 1,
            "linesRemoved": 0,
            "projectName": "web",
            "content": {
              "added": [],
              "removed": []
            },
            "duration": 0,
            "language": "php"
          }
        ]
      },
      "languageStats": {
        "php": 0
      },
      "changeFrequency": {
        "8": 0
      },
      "topFiles": [
        "c:\\Users\\thiag\\AppData\\Roaming\\Code\\User\\globalStorage\\yunusga.ftp-simple\\remote-workspace-temp\\37045e2986e0b0e4b66c2134e9be553d\\web\\head.php"
      ],
      "averageChangeSize": 219
    }
  },
  "totalActiveTime": 0,
  "totalProjects": 1,
  "totalFiles": 1,
  "mostActiveHours": [
    8
  ],
  "mostUsedLanguages": [
    "php"
  ]
}